csv2qif/__init__.py
csv2qif/csv2qif.py
csv2qif/transaction_writer.py
csv2qif-0.6.0.dist-info/LICENSE
csv2qif-0.6.0.dist-info/METADATA
csv2qif-0.6.0.dist-info/WHEEL
csv2qif-0.6.0.dist-info/entry_points.txt
csv2qif-0.6.0.dist-info/top_level.txt
csv2qif-0.6.0.dist-info/RECORD
