Metadata-Version: 2.1
Name: csv2qif
Version: 0.6.0
Summary: Convert financial transactions in CSV format to QIF files.
Author-email: Edward Bridges <github@eqbridges.com>
Project-URL: Homepage, https://github.com/ebridges/csv2qif
Project-URL: Bug Tracker, https://github.com/ebridges/csv2qif/issues
Classifier: Development Status :: 4 - Beta
Classifier: Intended Audience :: End Users/Desktop
Classifier: Intended Audience :: Financial and Insurance Industry
Classifier: Topic :: Home Automation
Classifier: Topic :: Office/Business :: Financial
Classifier: Topic :: Office/Business :: Financial :: Accounting
Classifier: Topic :: Utilities
Requires-Python: >=3.11
License-File: LICENSE
Provides-Extra: build
Requires-Dist: build ; extra == 'build'
Provides-Extra: dev
Requires-Dist: black ; extra == 'dev'
